pygmentize_faster.py
pygmentize_faster-1.0.1.dist-info/entry_points.txt
pygmentize_faster-1.0.1.dist-info/LICENSE
pygmentize_faster-1.0.1.dist-info/WHEEL
pygmentize_faster-1.0.1.dist-info/METADATA
pygmentize_faster-1.0.1.dist-info/RECORD
