Metadata-Version: 2.1
Name: pygmentize-faster
Version: 1.0.1
Summary: Provides a faster version of pygmentize
Home-page: https://github.com/joouha/pygmentize-faster
License: MIT
Keywords: pygments
Author: Josiah Outram Halstead
Author-email: josiah@halstead.email
Requires-Python: >=3.8,<4.0
Classifier: License :: OSI Approved :: MIT License
Classifier: Programming Language :: Python :: 3
Classifier: Programming Language :: Python :: 3.10
Classifier: Programming Language :: Python :: 3.8
Classifier: Programming Language :: Python :: 3.9
Requires-Dist: pygments-cache (>=0.1.3,<0.2.0)
